xmlxnat/__init__.py
xmlxnat/main.py
xmlxnat-0.0.0.dist-info/LICENSE.txt
xmlxnat-0.0.0.dist-info/METADATA
xmlxnat-0.0.0.dist-info/WHEEL
xmlxnat-0.0.0.dist-info/top_level.txt
xmlxnat-0.0.0.dist-info/RECORD
